[{
  "dateTime" : "05/29/21 00:00:00",
  "value" : "335"
},{
  "dateTime" : "05/30/21 00:00:00",
  "value" : "213"
},{
  "dateTime" : "05/31/21 00:00:00",
  "value" : "185"
},{
  "dateTime" : "06/01/21 00:00:00",
  "value" : "138"
},{
  "dateTime" : "06/02/21 00:00:00",
  "value" : "113"
},{
  "dateTime" : "06/03/21 00:00:00",
  "value" : "139"
},{
  "dateTime" : "06/04/21 00:00:00",
  "value" : "119"
},{
  "dateTime" : "06/05/21 00:00:00",
  "value" : "91"
},{
  "dateTime" : "06/06/21 00:00:00",
  "value" : "218"
},{
  "dateTime" : "06/07/21 00:00:00",
  "value" : "162"
},{
  "dateTime" : "06/08/21 00:00:00",
  "value" : "181"
},{
  "dateTime" : "06/09/21 00:00:00",
  "value" : "189"
},{
  "dateTime" : "06/10/21 00:00:00",
  "value" : "154"
},{
  "dateTime" : "06/11/21 00:00:00",
  "value" : "163"
},{
  "dateTime" : "06/12/21 00:00:00",
  "value" : "285"
},{
  "dateTime" : "06/13/21 00:00:00",
  "value" : "144"
},{
  "dateTime" : "06/14/21 00:00:00",
  "value" : "232"
},{
  "dateTime" : "06/15/21 00:00:00",
  "value" : "185"
},{
  "dateTime" : "06/16/21 00:00:00",
  "value" : "256"
},{
  "dateTime" : "06/17/21 00:00:00",
  "value" : "136"
},{
  "dateTime" : "06/18/21 00:00:00",
  "value" : "228"
},{
  "dateTime" : "06/19/21 00:00:00",
  "value" : "223"
},{
  "dateTime" : "06/20/21 00:00:00",
  "value" : "164"
},{
  "dateTime" : "06/21/21 00:00:00",
  "value" : "128"
},{
  "dateTime" : "06/22/21 00:00:00",
  "value" : "291"
},{
  "dateTime" : "06/23/21 00:00:00",
  "value" : "142"
},{
  "dateTime" : "06/24/21 00:00:00",
  "value" : "130"
},{
  "dateTime" : "06/25/21 00:00:00",
  "value" : "159"
},{
  "dateTime" : "06/26/21 00:00:00",
  "value" : "177"
},{
  "dateTime" : "06/27/21 00:00:00",
  "value" : "117"
}]